scbig/__init__.py
scbig/run_scbig.py
scbig/data/__init__.py
scbig/data/data_utils.py
scbig/data/graph.py
scbig/model/__init__.py
scbig/model/decoder.py
scbig/model/scbig.py
scbig/utils/__init__.py
scbig/utils/metric.py
scbig/utils/read.py
scbig/utils/utils.py
scbig-0.1.1.dist-info/LICENSE
scbig-0.1.1.dist-info/METADATA
scbig-0.1.1.dist-info/WHEEL
scbig-0.1.1.dist-info/top_level.txt
scbig-0.1.1.dist-info/RECORD
