Metadata-Version: 2.1
Name: scbig
Version: 0.1.1
Summary: scBiG for representation learning of single-cell gene expression data based on bipartite graph embedding
Home-page: https://github.com/sldyns/scBiG
Author: Kun Qian, Ting Li
Author-email: kun_qian@foxmail.com
Maintainer: Kun Qian
Maintainer-email: kun_qian@foxmail.com
License: MIT Licence
Keywords: single-cell RNA-sequencing,Graph node embedding,Dimensionality reduction
Platform: any
License-File: LICENSE
Requires-Dist: numpy
Requires-Dist: scanpy
Requires-Dist: h5py
Requires-Dist: torch
Requires-Dist: dgl
Requires-Dist: pandas
Requires-Dist: scipy
Requires-Dist: scikit-learn
Requires-Dist: louvain
